{
   "2628737308819456771": [
      {
         "actor": {
            "about": " ",
            "date_joined": 1544155907,
            "display_name": "Mateos Norian",
            "first_name": "Mateos",
            "id": "2628737308819456771",
            "is_active": true,
            "is_group": false,
            "last_name": "Norian",
            "phone": null,
            "profile_picture_url": "https://pics.venmo.com/16c9f68d-ca14-4d61-aeb1-09350f76377b?width=460&height=460&photoVersion=1",
            "username": "MateosNorian"
         },
         "amount": 4.0,
         "audience": "private",
         "date_completed": 1601151363,
         "date_created": 1601151363,
         "date_updated": 1601151363,
         "device_used": "iPhone",
         "id": "3106880046778811211",
         "note": "Dishwasher pods",
         "payment_id": "3106880046141276548",
         "payment_type": "charge",
         "status": "settled",
         "target": {
            "about": " ",
            "date_joined": 1528776595,
            "display_name": "Patrick Kuczynski",
            "first_name": "Patrick",
            "id": "2499756488130560590",
            "is_active": true,
            "is_group": false,
            "last_name": "Kuczynski",
            "phone": null,
            "profile_picture_url": "https://pics.venmo.com/19f9cfbb-ed69-457e-8c8a-f5cf2b349bde?width=460&height=460&photoVersion=2",
            "username": "Patkuzy"
         }
      }
   ],
   "2642540243189760484": [
      {
         "actor": {
            "about": " ",
            "date_joined": 1547936474,
            "display_name": "Darren Gray",
            "first_name": "Darren",
            "id": "2660451003400192422",
            "is_active": true,
            "is_group": false,
            "last_name": "Gray",
            "phone": null,
            "profile_picture_url": "https://pics.venmo.com/eba1a882-865b-4574-afa8-b94856090a2c?width=460&height=460&photoVersion=1",
            "username": "Darren-Gray-9"
         },
         "amount": null,
         "audience": "public",
         "date_completed": 1565805682,
         "date_created": 1565805682,
         "date_updated": 1565805682,
         "device_used": "iPhone",
         "id": "2810378986331308339",
         "note": "I love you kid",
         "payment_id": "2810378986046095874",
         "payment_type": "pay",
         "status": "settled",
         "target": {
            "about": " ",
            "date_joined": 1545801345,
            "display_name": "Adam Jurkiewicz",
            "first_name": "Adam",
            "id": "2642540243189760484",
            "is_active": true,
            "is_group": false,
            "last_name": "Jurkiewicz",
            "phone": null,
            "profile_picture_url": "https://pics.venmo.com/c96cdf8d-5898-427e-be90-ca5f6dc2034c?width=460&height=460&photoVersion=1",
            "username": "adamj0330"
         }
      },
      {
         "actor": {
            "about": " ",
            "date_joined": 1520719058,
            "display_name": "Jaemin Seo",
            "first_name": "Jaemin",
            "id": "2432134769803264022",
            "is_active": true,
            "is_group": false,
            "last_name": "Seo",
            "phone": null,
            "profile_picture_url": "https://pics.venmo.com/c4686795-ad69-4435-bf69-92c24bf9db9f?width=50&height=50&photoVersion=1&facebook=true",
            "username": "Jaemin-Seo"
         },
         "amount": null,
         "audience": "public",
         "date_completed": 1565132373,
         "date_created": 1565132373,
         "date_updated": 1565132373,
         "device_used": "iPhone",
         "id": "2804730862954873275",
         "note": "\ud83e\udd37\u200d\u2642\ufe0f",
         "payment_id": "2804730862568997605",
         "payment_type": "pay",
         "status": "settled",
         "target": {
            "about": " ",
            "date_joined": 1545801345,
            "display_name": "Adam Jurkiewicz",
            "first_name": "Adam",
            "id": "2642540243189760484",
            "is_active": true,
            "is_group": false,
            "last_name": "Jurkiewicz",
            "phone": null,
            "profile_picture_url": "https://pics.venmo.com/c96cdf8d-5898-427e-be90-ca5f6dc2034c?width=460&height=460&photoVersion=1",
            "username": "adamj0330"
         }
      },
      {
         "actor": {
            "about": " ",
            "date_joined": 1520719058,
            "display_name": "Jaemin Seo",
            "first_name": "Jaemin",
            "id": "2432134769803264022",
            "is_active": true,
            "is_group": false,
            "last_name": "Seo",
            "phone": null,
            "profile_picture_url": "https://pics.venmo.com/c4686795-ad69-4435-bf69-92c24bf9db9f?width=50&height=50&photoVersion=1&facebook=true",
            "username": "Jaemin-Seo"
         },
         "amount": null,
         "audience": "public",
         "date_completed": 1563742666,
         "date_created": 1563742666,
         "date_updated": 1563742666,
         "device_used": "iPhone",
         "id": "2793073157391516565",
         "note": "Food",
         "payment_id": "2793073156812702658",
         "payment_type": "pay",
         "status": "settled",
         "target": {
            "about": " ",
            "date_joined": 1545801345,
            "display_name": "Adam Jurkiewicz",
            "first_name": "Adam",
            "id": "2642540243189760484",
            "is_active": true,
            "is_group": false,
            "last_name": "Jurkiewicz",
            "phone": null,
            "profile_picture_url": "https://pics.venmo.com/c96cdf8d-5898-427e-be90-ca5f6dc2034c?width=460&height=460&photoVersion=1",
            "username": "adamj0330"
         }
      },
      {
         "actor": {
            "about": " ",
            "date_joined": 1503260163,
            "display_name": "Anastasia Loskutov",
            "first_name": "Anastasia",
            "id": "2285709142523904579",
            "is_active": true,
            "is_group": false,
            "last_name": "Loskutov",
            "phone": null,
            "profile_picture_url": "https://pics.venmo.com/2ee387c7-4a4d-4fd4-9b33-2483d50b4ceb?width=460&height=460&photoVersion=2",
            "username": "Anastasia-Loskutov"
         },
         "amount": null,
         "audience": "public",
         "date_completed": 1563483522,
         "date_created": 1563483522,
         "date_updated": 1563483522,
         "device_used": "iPhone",
         "id": "2790899298810724368",
         "note": "yum yums \ud83e\udd24",
         "payment_id": "2790899298424849339",
         "payment_type": "pay",
         "status": "settled",
         "target": {
            "about": " ",
            "date_joined": 1545801345,
            "display_name": "Adam Jurkiewicz",
            "first_name": "Adam",
            "id": "2642540243189760484",
            "is_active": true,
            "is_group": false,
            "last_name": "Jurkiewicz",
            "phone": null,
            "profile_picture_url": "https://pics.venmo.com/c96cdf8d-5898-427e-be90-ca5f6dc2034c?width=460&height=460&photoVersion=1",
            "username": "adamj0330"
         }
      },
      {
         "actor": {
            "about": " ",
            "date_joined": 1503260163,
            "display_name": "Anastasia Loskutov",
            "first_name": "Anastasia",
            "id": "2285709142523904579",
            "is_active": true,
            "is_group": false,
            "last_name": "Loskutov",
            "phone": null,
            "profile_picture_url": "https://pics.venmo.com/2ee387c7-4a4d-4fd4-9b33-2483d50b4ceb?width=460&height=460&photoVersion=2",
            "username": "Anastasia-Loskutov"
         },
         "amount": null,
         "audience": "public",
         "date_completed": 1563482443,
         "date_created": 1563482443,
         "date_updated": 1563482443,
         "device_used": "iPhone",
         "id": "2790890249851503463",
         "note": "code brown clean up",
         "payment_id": "2790890249323020374",
         "payment_type": "charge",
         "status": "settled",
         "target": {
            "about": " ",
            "date_joined": 1545801345,
            "display_name": "Adam Jurkiewicz",
            "first_name": "Adam",
            "id": "2642540243189760484",
            "is_active": true,
            "is_group": false,
            "last_name": "Jurkiewicz",
            "phone": null,
            "profile_picture_url": "https://pics.venmo.com/c96cdf8d-5898-427e-be90-ca5f6dc2034c?width=460&height=460&photoVersion=1",
            "username": "adamj0330"
         }
      },
      {
         "actor": {
            "about": " ",
            "date_joined": 1545801345,
            "display_name": "Adam Jurkiewicz",
            "first_name": "Adam",
            "id": "2642540243189760484",
            "is_active": true,
            "is_group": false,
            "last_name": "Jurkiewicz",
            "phone": null,
            "profile_picture_url": "https://pics.venmo.com/c96cdf8d-5898-427e-be90-ca5f6dc2034c?width=460&height=460&photoVersion=1",
            "username": "adamj0330"
         },
         "amount": null,
         "audience": "public",
         "date_completed": 1562799102,
         "date_created": 1562799102,
         "date_updated": 1562799102,
         "device_used": "iPhone",
         "id": "2785157963864604756",
         "note": "\ud83d\ude83\ud83c\udf55",
         "payment_id": "2785157963503895365",
         "payment_type": "pay",
         "status": "settled",
         "target": {
            "about": " ",
            "date_joined": 1519441377,
            "display_name": "Jacob Bayer",
            "first_name": "Jacob",
            "id": "2421416804745216120",
            "is_active": true,
            "is_group": false,
            "last_name": "Bayer",
            "phone": null,
            "profile_picture_url": "https://pics.venmo.com/f5aa43b8-8e07-46db-8e8d-dc206e104dcd?width=460&height=460&photoVersion=1",
            "username": "Jbayer222"
         }
      },
      {
         "actor": {
            "about": " ",
            "date_joined": 1520719058,
            "display_name": "Jaemin Seo",
            "first_name": "Jaemin",
            "id": "2432134769803264022",
            "is_active": true,
            "is_group": false,
            "last_name": "Seo",
            "phone": null,
            "profile_picture_url": "https://pics.venmo.com/c4686795-ad69-4435-bf69-92c24bf9db9f?width=50&height=50&photoVersion=1&facebook=true",
            "username": "Jaemin-Seo"
         },
         "amount": null,
         "audience": "public",
         "date_completed": 1562214281,
         "date_created": 1562214281,
         "date_updated": 1562214281,
         "device_used": "iPhone",
         "id": "2780252129477001651",
         "note": "\ud83e\udd37\u200d\u2642\ufe0f",
         "payment_id": "2780252129015628531",
         "payment_type": "pay",
         "status": "settled",
         "target": {
            "about": " ",
            "date_joined": 1545801345,
            "display_name": "Adam Jurkiewicz",
            "first_name": "Adam",
            "id": "2642540243189760484",
            "is_active": true,
            "is_group": false,
            "last_name": "Jurkiewicz",
            "phone": null,
            "profile_picture_url": "https://pics.venmo.com/c96cdf8d-5898-427e-be90-ca5f6dc2034c?width=460&height=460&photoVersion=1",
            "username": "adamj0330"
         }
      },
      {
         "actor": {
            "about": " ",
            "date_joined": 1547936474,
            "display_name": "Darren Gray",
            "first_name": "Darren",
            "id": "2660451003400192422",
            "is_active": true,
            "is_group": false,
            "last_name": "Gray",
            "phone": null,
            "profile_picture_url": "https://pics.venmo.com/eba1a882-865b-4574-afa8-b94856090a2c?width=460&height=460&photoVersion=1",
            "username": "Darren-Gray-9"
         },
         "amount": null,
         "audience": "public",
         "date_completed": 1561050849,
         "date_created": 1561050849,
         "date_updated": 1561050849,
         "device_used": "iPhone",
         "id": "2770492554913776415",
         "note": "Yeezys",
         "payment_id": "2770492554494345806",
         "payment_type": "pay",
         "status": "settled",
         "target": {
            "about": " ",
            "date_joined": 1545801345,
            "display_name": "Adam Jurkiewicz",
            "first_name": "Adam",
            "id": "2642540243189760484",
            "is_active": true,
            "is_group": false,
            "last_name": "Jurkiewicz",
            "phone": null,
            "profile_picture_url": "https://pics.venmo.com/c96cdf8d-5898-427e-be90-ca5f6dc2034c?width=460&height=460&photoVersion=1",
            "username": "adamj0330"
         }
      },
      {
         "actor": {
            "about": " ",
            "date_joined": 1545801345,
            "display_name": "Adam Jurkiewicz",
            "first_name": "Adam",
            "id": "2642540243189760484",
            "is_active": true,
            "is_group": false,
            "last_name": "Jurkiewicz",
            "phone": null,
            "profile_picture_url": "https://pics.venmo.com/c96cdf8d-5898-427e-be90-ca5f6dc2034c?width=460&height=460&photoVersion=1",
            "username": "adamj0330"
         },
         "amount": null,
         "audience": "public",
         "date_completed": 1555486542,
         "date_created": 1555486542,
         "date_updated": 1555486542,
         "device_used": "iPhone",
         "id": "2723815770873136041",
         "note": "Prom pics pt2",
         "payment_id": "2723815770378208101",
         "payment_type": "pay",
         "status": "settled",
         "target": {
            "about": " ",
            "date_joined": 1515200629,
            "display_name": "Courtney Callen",
            "first_name": "Courtney",
            "id": "2385842832146432810",
            "is_active": true,
            "is_group": false,
            "last_name": "Callen",
            "phone": null,
            "profile_picture_url": "https://pics.venmo.com/5af5e997-16ac-4c3f-9db8-622f9f1e7df7?width=460&height=460&photoVersion=4",
            "username": "courtneycallen"
         }
      },
      {
         "actor": {
            "about": " ",
            "date_joined": 1545801345,
            "display_name": "Adam Jurkiewicz",
            "first_name": "Adam",
            "id": "2642540243189760484",
            "is_active": true,
            "is_group": false,
            "last_name": "Jurkiewicz",
            "phone": null,
            "profile_picture_url": "https://pics.venmo.com/c96cdf8d-5898-427e-be90-ca5f6dc2034c?width=460&height=460&photoVersion=1",
            "username": "adamj0330"
         },
         "amount": null,
         "audience": "public",
         "date_completed": 1555056666,
         "date_created": 1555056666,
         "date_updated": 1555056666,
         "device_used": "iPhone",
         "id": "2720209705283616789",
         "note": "Prom pics",
         "payment_id": "2720209704914518043",
         "payment_type": "pay",
         "status": "settled",
         "target": {
            "about": " ",
            "date_joined": 1515200629,
            "display_name": "Courtney Callen",
            "first_name": "Courtney",
            "id": "2385842832146432810",
            "is_active": true,
            "is_group": false,
            "last_name": "Callen",
            "phone": null,
            "profile_picture_url": "https://pics.venmo.com/5af5e997-16ac-4c3f-9db8-622f9f1e7df7?width=460&height=460&photoVersion=4",
            "username": "courtneycallen"
         }
      },
      {
         "actor": {
            "about": " ",
            "date_joined": 1547936474,
            "display_name": "Darren Gray",
            "first_name": "Darren",
            "id": "2660451003400192422",
            "is_active": true,
            "is_group": false,
            "last_name": "Gray",
            "phone": null,
            "profile_picture_url": "https://pics.venmo.com/eba1a882-865b-4574-afa8-b94856090a2c?width=460&height=460&photoVersion=1",
            "username": "Darren-Gray-9"
         },
         "amount": null,
         "audience": "public",
         "date_completed": 1554018471,
         "date_created": 1554018471,
         "date_updated": 1554018471,
         "device_used": "iPhone",
         "id": "2711500697664225935",
         "note": "\ud83c\udf82\ud83c\udf89",
         "payment_id": "2711500697228017759",
         "payment_type": "pay",
         "status": "settled",
         "target": {
            "about": " ",
            "date_joined": 1545801345,
            "display_name": "Adam Jurkiewicz",
            "first_name": "Adam",
            "id": "2642540243189760484",
            "is_active": true,
            "is_group": false,
            "last_name": "Jurkiewicz",
            "phone": null,
            "profile_picture_url": "https://pics.venmo.com/c96cdf8d-5898-427e-be90-ca5f6dc2034c?width=460&height=460&photoVersion=1",
            "username": "adamj0330"
         }
      },
      {
         "actor": {
            "about": " ",
            "date_joined": 1547936474,
            "display_name": "Darren Gray",
            "first_name": "Darren",
            "id": "2660451003400192422",
            "is_active": true,
            "is_group": false,
            "last_name": "Gray",
            "phone": null,
            "profile_picture_url": "https://pics.venmo.com/eba1a882-865b-4574-afa8-b94856090a2c?width=460&height=460&photoVersion=1",
            "username": "Darren-Gray-9"
         },
         "amount": null,
         "audience": "public",
         "date_completed": 1552800473,
         "date_created": 1552800473,
         "date_updated": 1552800473,
         "device_used": "iPhone",
         "id": "2701283387783512881",
         "note": "For niki",
         "payment_id": "2701283387389247650",
         "payment_type": "pay",
         "status": "settled",
         "target": {
            "about": " ",
            "date_joined": 1545801345,
            "display_name": "Adam Jurkiewicz",
            "first_name": "Adam",
            "id": "2642540243189760484",
            "is_active": true,
            "is_group": false,
            "last_name": "Jurkiewicz",
            "phone": null,
            "profile_picture_url": "https://pics.venmo.com/c96cdf8d-5898-427e-be90-ca5f6dc2034c?width=460&height=460&photoVersion=1",
            "username": "adamj0330"
         }
      }
   ]
}